[
  {
    "frame": "frame_0000.jpg",
    "detections": []
  },
  {
    "frame": "frame_0001.jpg",
    "detections": []
  },
  {
    "frame": "frame_0002.jpg",
    "detections": []
  },
  {
    "frame": "frame_0003.jpg",
    "detections": []
  },
  {
    "frame": "frame_0004.jpg",
    "detections": []
  },
  {
    "frame": "frame_0005.jpg",
    "detections": []
  },
  {
    "frame": "frame_0006.jpg",
    "detections": []
  },
  {
    "frame": "frame_0007.jpg",
    "detections": []
  },
  {
    "frame": "frame_0008.jpg",
    "detections": []
  },
  {
    "frame": "frame_0009.jpg",
    "detections": []
  },
  {
    "frame": "frame_0010.jpg",
    "detections": []
  },
  {
    "frame": "frame_0011.jpg",
    "detections": []
  },
  {
    "frame": "frame_0012.jpg",
    "detections": []
  },
  {
    "frame": "frame_0013.jpg",
    "detections": []
  },
  {
    "frame": "frame_0014.jpg",
    "detections": []
  },
  {
    "frame": "frame_0015.jpg",
    "detections": []
  },
  {
    "frame": "frame_0016.jpg",
    "detections": []
  },
  {
    "frame": "frame_0017.jpg",
    "detections": []
  },
  {
    "frame": "frame_0018.jpg",
    "detections": []
  }
]